[
  {
    "id": 1,
    "question": "একটি কণার উপর F = (-2i + 3j + 3k) নিউটন বল প্রয়োগের ফলে কণাটি (3, -4, -2) বিন্দু থেকে (-2, 3, 5) বিন্দুতে স্থানান্তরিত হয়। বল কর্তৃক সম্পাদিত কাজের পরিমাণ কত?",
    "options": {
      "A": "52 J",
      "B": "59 J",
      "C": "48 J",
      "D": "54 J"
    },
    "correctAnswer": "A"
  },
  {
    "id": 2,
    "question": "196 ms⁻¹ বেগে একটি পাথরকে উপরে নিক্ষেপ করা হলো। 10 sec পরে পাথরটির বেগ কত?",
    "options": {
      "A": "0 ms⁻¹",
      "B": "9.8 ms⁻¹",
      "C": "49 ms⁻¹",
      "D": "98 ms⁻¹"
    },
    "correctAnswer": "D"
  },
  {
    "id": 3,
    "question": "একটি গাড়ি 10 ms⁻¹ গতিতে চলছে। কত গতিতে চালালে গাড়িটির গতিশক্তি দ্বিগুণ হবে?",
    "options": {
      "A": "40.1 ms⁻¹",
      "B": "10 ms⁻¹",
      "C": "100 ms⁻¹",
      "D": "14.1 ms⁻¹"
    },
    "correctAnswer": "D"
  },
  {
    "id": 4,
    "question": "কৌণিক বেগের মাত্রা সমীকরণ—",
    "options": {
      "A": "MLT⁻¹",
      "B": "LT⁻¹",
      "C": "LT⁻²",
      "D": "T⁻¹"
    },
    "correctAnswer": "D"
  },
  {
    "id": 5,
    "question": "কোনো বস্তুর নিক্ষেপণ বেগ মুক্তিবেগের চেয়ে বেশি হলে বস্তুটি—",
    "options": {
      "A": "উপগ্রহে পরিণত হবে",
      "B": "পরাবৃত্তাকার পথে পৃথিবী ছেড়ে যাবে",
      "C": "পৃথিবীতে ফিরে আসবে",
      "D": "অধিবৃত্তাকার পথে পৃথিবী ছেড়ে যাবে"
    },
    "correctAnswer": "D"
  },
  {
    "id": 6,
    "question": "একটি রডের ইয়ং এর গুণাঙ্ক Y = 2 × 10¹¹ Nm⁻² এবং তার উপর 200 N বল প্রয়োগ করা হলে রডের প্রস্থচ্ছেদ 0.1 cm² এবং দৈর্ঘ্য পরিবর্তন ΔL = 0.2 mm হয়। রডের প্রাথমিক দৈর্ঘ্য কত?",
    "options": {
      "A": "1.0 m",
      "B": "0.2 m",
      "C": "0.5 m",
      "D": "2.0 m"
    },
    "correctAnswer": "D"
  },
  {
    "id": 7,
    "question": "27°C তাপমাত্রায় ও 6 × 10⁵ Pa চাপে কোন গ্যাসের আয়তন 100 cm³ হলে, 77°C তাপমাত্রা ও 10⁶ Pa চাপে এর আয়তন কত?",
    "options": {
      "A": "60 cm³",
      "B": "70 cm³",
      "C": "75 cm³",
      "D": "80 cm³"
    },
    "correctAnswer": "B"
  },
  {
    "id": 8,
    "question": "বোর মডেল অনুসারে, n তম কক্ষপথে ইলেকট্রনের মোট শক্তি Eₙ হলে, নিচের কোনটি সঠিক?",
    "options": {
      "A": "Eₙ ∝ 1/n",
      "B": "Eₙ ∝ 1/n²",
      "C": "Eₙ ∝ n",
      "D": "Eₙ ∝ n²"
    },
    "correctAnswer": "B"
  },
  {
    "id": 9,
    "question": "একটি কার্নো ইঞ্জিন 400 K তাপমাত্রার উৎস থেকে 300 cal তাপ গ্রহণ করে এবং তাপ গ্রাহকে 225 cal তাপ বর্জন করে। তাপ গ্রাহকের তাপমাত্রা কত?",
    "options": {
      "A": "425 K",
      "B": "525 K",
      "C": "325 K",
      "D": "300 K"
    },
    "correctAnswer": "D"
  },
  {
    "id": 10,
    "question": "ইয়ং এর দ্বিচিড় পরীক্ষায় পরপর দুটি উজ্জ্বল ডোরার মধ্যবর্তী দূরত্ব 5.25 × 10⁻⁴ m। চিড় দুইটি থেকে পর্দার দূরত্ব 0.9 m এবং আলোর তরঙ্গদৈর্ঘ্য 5.25 × 10⁻⁷ m হলে চিড় দুইটির মধ্যে দূরত্ব কত?",
    "options": {
      "A": "6 mm",
      "B": "6 cm",
      "C": "9 mm",
      "D": "9 cm"
    },
    "correctAnswer": "C"
  },
  {
    "id": 11,
    "question": "তিনটি সমান মানের ধারক সমান্তরালে যুক্ত থাকলে বর্তনীর তুল্য ধারকত্ব শ্রেণি সমবায়ে যুক্ত তুল্য ধারকত্বের তুলনায় কত?",
    "options": {
      "A": "এক-তৃতীয়াংশ",
      "B": "3 গুণ",
      "C": "9 গুণ",
      "D": "এক-নবমাংশ"
    },
    "correctAnswer": "C"
  },
  {
    "id": 12,
    "question": "তাড়িৎচৌম্বকীয় তরঙ্গ নিচের কোন দিক বরাবর অগ্রসর হয়?",
    "options": {
      "A": "E",
      "B": "B",
      "C": "E × B",
      "D": "E . B"
    },
    "correctAnswer": "C"
  },
  {
    "id": 13,
    "question": "200 পাক বিশিষ্ট একটি কুণ্ডলীতে চৌম্বক প্রবাহ প্রতি সেকেন্ডে 0.02 ওয়েবার থেকে 0.06 ওয়েবারে পরিবর্তিত হলে, কুণ্ডলীতে ইলেকট্রোমোটিভ ফোর্স (EMF) কত হবে?",
    "options": {
      "A": "2 V",
      "B": "4 V",
      "C": "8 V",
      "D": "কোনোটিই নয়"
    },
    "correctAnswer": "C"
  },
  {
    "id": 14,
    "question": "কোন পুকুরের তলদেশে একটি মাছকে খাড়াভাবে দেখলে 3 m নিচে দেখা যায়। পানির প্রতিসরাঙ্ক 4/3 হলে, পুকুরটির প্রকৃত গভীরতা কত?",
    "options": {
      "A": "2.25 m",
      "B": "2.67 m",
      "C": "1.33 m",
      "D": "4.0 m"
    },
    "correctAnswer": "D"
  },
  {
    "id": 15,
    "question": "একটি অভিসারী লেন্সের ফোকাস দৈর্ঘ্য 20 cm হলে, 30 cm দূরত্বে রাখা একটি বস্তুর স্পষ্ট বিম্ব তৈরি হয়। যদি বস্তুটি লেন্স থেকে 10 cm দূরত্বে সরিয়ে আনা হয়, তাহলে বিম্বের ক্ষেত্রে নিচের কোনটি সঠিক?",
    "options": {
      "A": "বিম্বটি বাস্তব হবে এবং লেন্স থেকে আরো দূরে সরে যাবে",
      "B": "বিম্বটি অবাস্তব হবে এবং লেন্সের পেছনে চলে যাবে",
      "C": "বিম্বটি বাস্তব হবে এবং লেন্সের কাছাকাছি চলে যাবে",
      "D": "বিম্বটি অদৃশ্য হয়ে যাবে কারণ কোনো প্রতিসরণ হবে না"
    },
    "correctAnswer": "B"
  },
  {
    "id": 16,
    "question": "নিম্নের বর্তনীতে A=+5 V ও B=0 V হলে, বর্তনীর আউটপুট ভোল্টেজ কত হবে?",
    "options": {
      "A": "-5 V",
      "B": "+5 V",
      "C": "0 V",
      "D": "কোনোটিই না"
    },
    "correctAnswer": "C"
  },
  {
    "id": 17,
    "question": "একটি পাতলা ফাঁপা পরিবাহী গোলকের ব্যাসার্ধ R = 15 cm। এতে Q = 6 × 10⁻⁶ C আধান প্রদান করা হয়েছে। গোলকের কেন্দ্রে বৈদ্যুতিক ক্ষেত্রের মান কত?",
    "options": {
      "A": "0 NC⁻¹",
      "B": "2.4 × 10⁶ NC⁻¹",
      "C": "4.8 × 10⁶ NC⁻¹",
      "D": "6.0 × 10⁶ NC⁻¹"
    },
    "correctAnswer": "A"
  },
  {
    "id": 18,
    "question": "নিচের কোনটি আদর্শ গ্যাসের বৈশিষ্ট্য নয়?",
    "options": {
      "A": "গ্যাস অণুগুলোর মধ্যে কোনো আন্তঃআণবিক বল থাকে না",
      "B": "গ্যাসের আণবিক গতিশক্তি নির্দিষ্ট তাপমাত্রায় সবসময় একই থাকে",
      "C": "গ্যাস অণুগুলোর মধ্যে স্থিতিস্থাপক সংঘর্ষ হয়",
      "D": "গ্যাসের আণবিক গতি ব্রাউনীয় গতির সাথে সম্পর্কিত থাকে"
    },
    "correctAnswer": "D"
  },
  {
    "id": 19,
    "question": "একটি কমন বেস ট্রানজিস্টরের অ্যামিটার প্রবাহ 1.25 mA এবং কালেক্টর প্রবাহ 8 × 10⁻⁴ A হলে, বেস প্রবাহ কত হবে?",
    "options": {
      "A": "4.5 × 10⁻⁴ A",
      "B": "3.5 A",
      "C": "0.3 × 10⁻³ A",
      "D": "3.3 × 10⁻³ mA"
    },
    "correctAnswer": "A"
  },
  {
    "id": 20,
    "question": "দৈর্ঘ্য L ও প্রস্থচ্ছেদ A বিশিষ্ট একটি তারের দৈর্ঘ্য বরাবর F বল প্রয়োগ করায় দৈর্ঘ্য l পরিমাণ বৃদ্ধি পায়। তারটিতে কৃতকাজের পরিমাণ কত?",
    "options": {
      "A": "F × L",
      "B": "(F × L) / 2",
      "C": "(F × l) / 2",
      "D": "(F × l) / 2A"
    },
    "correctAnswer": "C"
  },
  {
    "id": 21,
    "question": "50 kg ভরের একটি স্থির বস্তুর ওপর 5 sec ব্যাপী 10 N বল প্রযুক্ত হলো, বস্তুটির বেগের পরিবর্তন কত হবে?",
    "options": {
      "A": "1 ms⁻¹",
      "B": "10 ms⁻¹",
      "C": "50 ms⁻¹",
      "D": "0.5 ms⁻¹"
    },
    "correctAnswer": "A"
  },
  {
    "id": 22,
    "question": "সরল ছন্দিত গতিসম্পন্ন একটি কণার পর্যায়কাল 1 মিনিট হলে কৌণিক কম্পাঙ্ক কত rad/s?",
    "options": {
      "A": "0.08",
      "B": "0.10",
      "C": "0.14",
      "D": "0.16"
    },
    "correctAnswer": "B"
  },
  {
    "id": 23,
    "question": "একটি p-n জংশনের বিভব পার্থক্য 2.0 V থেকে 2.5 V করা হলো। এতে তড়িৎ প্রবাহ 500 mA পরিবর্তিত হলো। গতীয় রোধ কত?",
    "options": {
      "A": "0.1 Ω",
      "B": "0.5 Ω",
      "C": "1.0 Ω",
      "D": "1.1 Ω"
    },
    "correctAnswer": "C"
  },
  {
    "id": 24,
    "question": "50 পাক সংখ্যা ও 0.5 m দৈর্ঘ্য বিশিষ্ট একটি কুণ্ডলীর মধ্যে 2 A তড়িৎ প্রবাহিত হলে কুণ্ডলীর চারপাশে চৌম্বক ক্ষেত্রের শক্তি কত?",
    "options": {
      "A": "π × 10⁻⁴ Tesla",
      "B": "2π × 10⁻⁵ Tesla",
      "C": "5 × 10⁻⁵ Tesla",
      "D": "8π × 10⁻⁵ Tesla"
    },
    "correctAnswer": "D"
  },
  {
    "id": 25,
    "question": "তরঙ্গমুখ সংক্রান্ত নীতি প্রদান করেন—",
    "options": {
      "A": "ইয়ং",
      "B": "ফ্রেনেল",
      "C": "ফ্রনহফার",
      "D": "হাইগেনস"
    },
    "correctAnswer": "D"
  },
  {
    "id": 26,
    "question": "কোন ফেনলটির অম্লীয় ক্ষমতা সর্বোচ্চ?",
    "options": {
      "A": "ফেনল",
      "B": "p-মিথাইলফেনল",
      "C": "p-নাইট্রোফেনল",
      "D": "p-ক্লোরোফেনল"
    },
    "correctAnswer": "C"
  },
  {
    "id": 27,
    "question": "CH₂ = CH - C ≡ CH যৌগটির IUPAC নাম কী?",
    "options": {
      "A": "বিউটিন -১, ৩-আইন",
      "B": "বিউট-১-ইন-৩-আইন",
      "C": "বিউট-১-আইন-৩-ইন",
      "D": "বিউট-১.৩-ইন-আইন"
    },
    "correctAnswer": "B"
  },
  {
    "id": 28,
    "question": "আইসোনাইট্রাইল কার্যকরী মূলক কোনটি?",
    "options": {
      "A": "-CNS",
      "B": "-NC",
      "C": "-CN",
      "D": "-CSN"
    },
    "correctAnswer": "B"
  },
  {
    "id": 29,
    "question": "কোন জৈব যৌগটি NaNH₂ এর সাথে বিক্রিয়া দেয়?",
    "options": {
      "A": "CH₃CH = CH₂",
      "B": "CH₃C ≡ CCH₃",
      "C": "CH₃CH = CHCH₃",
      "D": "CH₃C ≡ CH"
    },
    "correctAnswer": "D"
  },
  {
    "id": 30,
    "question": "Sₙ2 বিক্রিয়ার ক্ষেত্রে কোন তথ্যটি সঠিক নয়?",
    "options": {
      "A": "জ্যামিতিক কাঠামো অপরিবর্তিত থাকে",
      "B": "বিক্রিয়াটি এক ধাপেই সম্পন্ন হয়",
      "C": "বিক্রিয়াটি দ্বিতীয় ক্রম অনুসরণ করে",
      "D": "শক্তিশালী নিউক্লিওফাইলের প্রভাবে সম্পন্ন হয়"
    },
    "correctAnswer": "A"
  },
  {
    "id": 31,
    "question": "কোন যৌগটি হ্যালোফর্ম বিক্রিয়া দেয়?",
    "options": {
      "A": "CH₃COCl",
      "B": "CH₃CONH₂",
      "C": "CH₃COOH",
      "D": "CH₃COCH₃"
    },
    "correctAnswer": "D"
  },
  {
    "id": 32,
    "question": "কোন যৌগে দুটি কাইরাল কার্বন আছে?",
    "options": {
      "A": "2-হাইড্রক্সি প্রোপানোয়িক এসিড",
      "B": "বিউটেন-2,3-ডাইঅল",
      "C": "2-মিথাইল প্রোপেন-2-অল",
      "D": "বিউটেন-2-অল"
    },
    "correctAnswer": "B"
  },
  {
    "id": 33,
    "question": "CH₃-CH(Cl)-CH₂-CH₃ + KOH(alc) -> CH₃CH=CHCH₃; বিক্রিয়াটি কোন নিয়ম অনুসারে ঘটে?",
    "options": {
      "A": "মারকনিকভ",
      "B": "বিপরীত মারকনিকভ",
      "C": "প্রতিস্থাপন",
      "D": "সাইজেফ"
    },
    "correctAnswer": "D"
  },
  {
    "id": 34,
    "question": "কোন জোড়া আইসোটোন?",
    "options": {
      "A": "¹²C, ¹³C",
      "B": "¹⁴C, ¹⁶O",
      "C": "⁶⁴Cu, ⁶⁴Zn",
      "D": "¹⁴C, ¹⁴N"
    },
    "correctAnswer": "B"
  },
  {
    "id": 35,
    "question": "250 mL NaOH দ্রবণে 5 g NaOH দ্রবীভূত থাকলে ঐ দ্রবণের মোলার ঘনমাত্রা কত?",
    "options": {
      "A": "0.1",
      "B": "0.5",
      "C": "1.25",
      "D": "0.125"
    },
    "correctAnswer": "B"
  },
  {
    "id": 36,
    "question": "বোর পরমাণু মডেল অনুযায়ী পঞ্চম শক্তিস্তরের একটি ইলেকট্রনের কৌণিক ভরবেগ কোনটি?",
    "options": {
      "A": "25h/π",
      "B": "h/π",
      "C": "5h/2π",
      "D": "2.5h/π"
    },
    "correctAnswer": "D"
  },
  {
    "id": 37,
    "question": "কোনটি লুইস এসিড নয়?",
    "options": {
      "A": "BeCl₂",
      "B": "AlCl₃",
      "C": "SO₂",
      "D": "BF₃"
    },
    "correctAnswer": "C"
  },
  {
    "id": 38,
    "question": "আয়নীকরণ শক্তির সঠিক ক্রম কোনটি?",
    "options": {
      "A": "Be < B < N < O",
      "B": "B < Be < N < O",
      "C": "Be < B < O < N",
      "D": "B < Be < O < N"
    },
    "correctAnswer": "D"
  },
  {
    "id": 39,
    "question": "0.01 M NaCl দ্রবণের ঘনমাত্রা ppm এককে কত?",
    "options": {
      "A": "558",
      "B": "585",
      "C": "858",
      "D": "354"
    },
    "correctAnswer": "B"
  },
  {
    "id": 40,
    "question": "একটি দ্রবণের pOH = 3 হলে H₃O⁺ এর মোলার ঘনমাত্রা কত?",
    "options": {
      "A": "1 × 10⁻³",
      "B": "1 × 10⁻¹¹",
      "C": "1 × 10⁻⁷",
      "D": "1 × 10⁻¹⁴"
    },
    "correctAnswer": "B"
  },
  {
    "id": 41,
    "question": "কোন যৌগে সবচেয়ে শক্তিশালী H-বন্ধন ঘটে?",
    "options": {
      "A": "H₂O",
      "B": "H₂S",
      "C": "HF",
      "D": "NH₃"
    },
    "correctAnswer": "C"
  },
  {
    "id": 42,
    "question": "কোন অণুর বন্ধন কোণের মান সবচেয়ে কম?",
    "options": {
      "A": "CH₄",
      "B": "H₂O",
      "C": "NH₃",
      "D": "BCl₃"
    },
    "correctAnswer": "B"
  },
  {
    "id": 43,
    "question": "কোন যৌগের গঠন চতুস্তলকীয় নয়?",
    "options": {
      "A": "CCl₄",
      "B": "NH₄⁺",
      "C": "BH₄⁻",
      "D": "SF₄"
    },
    "correctAnswer": "D"
  },
  {
    "id": 44,
    "question": "ভ্যানডার ওয়ালস সমীকরণের ধ্রুবক 'a' দ্বারা কী বুঝায়?",
    "options": {
      "A": "গ্যাসের গতিশক্তি",
      "B": "আন্তঃআণবিক আকর্ষণ",
      "C": "গ্যাসের আয়তন",
      "D": "আন্তঃআণবিক বিকর্ষণ"
    },
    "correctAnswer": "B"
  },
  {
    "id": 45,
    "question": "কোন ১ম ক্রম বিক্রিয়ায় অর্ধ্যযু 5 মিনিট হলে বিক্রিয়াটির হার ধ্রুবক কত?",
    "options": {
      "A": "2.3 × 10⁻⁴",
      "B": "2.3 × 10⁻³",
      "C": "2.6 × 10⁻³",
      "D": "2.4 × 10⁻⁴"
    },
    "correctAnswer": "B"
  },
  {
    "id": 46,
    "question": "নাইট্রোজেনকে আদর্শ গ্যাস ধরলে কত গ্রাম নাইট্রোজেনের জন্য PV = 0.02RT সমীকরণটি প্রযোজ্য?",
    "options": {
      "A": "0.14",
      "B": "0.28",
      "C": "0.56",
      "D": "0.65"
    },
    "correctAnswer": "C"
  },
  {
    "id": 47,
    "question": "গ্যাসীয় অবস্থায় কোন বিক্রিয়ার সাম্যবস্থায় Kₚ ও K꜀ এর মান সমান?",
    "options": {
      "A": "PCl₅ ⇌ PCl₃ + Cl₂",
      "B": "2SO₂ + O₂ ⇌ 2SO₃",
      "C": "N₂ + 3H₂ ⇌ 2NH₃",
      "D": "H₂ + I₂ ⇌ 2HI"
    },
    "correctAnswer": "D"
  },
  {
    "id": 48,
    "question": "25°C তাপমাত্রায় 1 atm চাপে 4 L O₂ গ্যাসকে 0.8 L এ সংকুচিত করতে কত চাপ প্রয়োগ করতে হবে?",
    "options": {
      "A": "5 atm",
      "B": "4 atm",
      "C": "3 atm",
      "D": "2 atm"
    },
    "correctAnswer": "A"
  },
  {
    "id": 49,
    "question": "গ্যাসের গড় গতিবেগের সঠিক সমীকরণ কোনটি?",
    "options": {
      "A": "c = √(8RT/πM)",
      "B": "c = √(3RT/M)",
      "C": "α = √(2RT/M)",
      "D": "c = √(2RT/M)"
    },
    "correctAnswer": "A"
  },
  {
    "id": 50,
    "question": "0.5 মোল Al ক্যাথোডে জমা করতে কী পরিমাণ বিদ্যুৎ লাগবে?",
    "options": {
      "A": "1 F",
      "B": "3 F",
      "C": "1.5 F",
      "D": "2 F"
    },
    "correctAnswer": "C"
  },
  {
    "id": 51,
    "question": "গ্লোবাল ভিলেজ প্রতিষ্ঠার ক্ষেত্রে নিচের কোন উপাদানটির ভূমিকা সবচেয়ে বেশি?",
    "options": {
      "A": "ইন্টারনেট",
      "B": "রেডিও",
      "C": "টেলিভিশন",
      "D": "টেলিফোন"
    },
    "correctAnswer": "A"
  },
  {
    "id": 52,
    "question": "কোন প্রযুক্তিটি কৃত্রিম বুদ্ধিমত্তার সাথে সম্পর্কিত?",
    "options": {
      "A": "ডাটা এন্ট্রি",
      "B": "স্প্রেডশিট",
      "C": "ওয়াই-ফাই",
      "D": "মেশিন লার্নিং"
    },
    "correctAnswer": "D"
  },
  {
    "id": 53,
    "question": "যে লজিক বর্তনী আলফা নিউমেরিক ক্যারেক্টারকে বাইনারি কোডে পরিণত করে তাকে কী বলে?",
    "options": {
      "A": "রেজিস্টার",
      "B": "এনকোডার",
      "C": "ডিকোডার",
      "D": "অ্যাডার"
    },
    "correctAnswer": "B"
  },
  {
    "id": 54,
    "question": "রেডিও এবং টেলিভিশনের সম্প্রচার কোন ধরনের কমিউনিকেশন মোড?",
    "options": {
      "A": "সিমপ্লেক্স এবং ইউনিকাস্ট",
      "B": "হাফ-ডুপ্লেক্স এবং ইউনিকাস্ট",
      "C": "সিমপ্লেক্স এবং ব্রডকাস্ট",
      "D": "ফুল-ডুপ্লেক্স এবং ব্রডকাস্ট"
    },
    "correctAnswer": "C"
  },
  {
    "id": 55,
    "question": "নিচের কোন পরিপূরক পদ্ধতিটি কম্পিউটারে ব্যবহৃত হয়?",
    "options": {
      "A": "১-এর পরিপূরক",
      "B": "২-এর পরিপূরক",
      "C": "১০-এর পরিপূরক",
      "D": "৯-এর পরিপূরক"
    },
    "correctAnswer": "B"
  },
  {
    "id": 56,
    "question": "হাইড্রার কোন নেমাটোসিস্টে হিপনোটক্সিন থাকে?",
    "options": {
      "A": "ভলভেন্ট",
      "B": "পেনিট্র্যান্ট",
      "C": "স্টেরিওগ্লুটিন্যান্ট",
      "D": "স্ট্রেপটোলিন গ্লুটিন্যান্ট"
    },
    "correctAnswer": "B"
  },
  {
    "id": 57,
    "question": "কোন পর্বের প্রাণীর স্নায়ুতন্ত্র মই-এর মত?",
    "options": {
      "A": "Annelida",
      "B": "Nematoda",
      "C": "Platyhelminthes",
      "D": "Chordata"
    },
    "correctAnswer": "C"
  },
  {
    "id": 58,
    "question": "কোন পর্বের প্রাণীতে Planula-লার্ভা দশা দেখা যায়?",
    "options": {
      "A": "Ctenophora",
      "B": "Echinodermata",
      "C": "Platyhelminthes",
      "D": "Cnidaria"
    },
    "correctAnswer": "D"
  },
  {
    "id": 59,
    "question": "ঘাস ফড়িং-এর উদরে কত জোড়া শ্বাসরন্ধ্র থাকে?",
    "options": {
      "A": "10 জোড়া",
      "B": "08 জোড়া",
      "C": "6 জোড়া",
      "D": "12 জোড়া"
    },
    "correctAnswer": "B"
  },
  {
    "id": 60,
    "question": "রুই মাছের হৃৎপিণ্ড কয় প্রকোষ্ঠ বিশিষ্ট?",
    "options": {
      "A": "6",
      "B": "5",
      "C": "4",
      "D": "2"
    },
    "correctAnswer": "D"
  },
  {
    "id": 61,
    "question": "শর্করা জাতীয় খাদ্যের শোষণ নিয়ন্ত্রণকারী হরমোন কোনটি?",
    "options": {
      "A": "ইনসুলিন",
      "B": "গ্লুকাগন",
      "C": "থাইরক্সিন",
      "D": "গ্লুকোকরটিকয়েড"
    },
    "correctAnswer": "D"
  },
  {
    "id": 62,
    "question": "লাল-সবুজ বর্ণান্ধতা কোন ধরনের রোগ?",
    "options": {
      "A": "সেক্স লিমিটেড",
      "B": "সেক্স ইনফ্লুয়েন্সড",
      "C": "সেক্স লিংকড",
      "D": "সেক্স রিভার্সেল"
    },
    "correctAnswer": "C"
  },
  {
    "id": 63,
    "question": "কোন উদ্ভিদে দ্বি-নিষেক দেখা যায়?",
    "options": {
      "A": "Ginkgo",
      "B": "Gnetum",
      "C": "Ephedra",
      "D": "Cycas"
    },
    "correctAnswer": "C"
  },
  {
    "id": 64,
    "question": "হলুদে কোন ধরনের রূপান্তরিত কাণ্ড দেখা যায়?",
    "options": {
      "A": "রানার",
      "B": "টিউবার",
      "C": "বাল্ব",
      "D": "রাইজোম"
    },
    "correctAnswer": "D"
  },
  {
    "id": 65,
    "question": "আবৃতবীজী উদ্ভিদের এন্ডোস্পার্ম কোন ধরনের?",
    "options": {
      "A": "হ্যাপ্লয়েড",
      "B": "ডিপ্লয়েড",
      "C": "ট্রিপ্লয়েড",
      "D": "টেট্রাপ্লয়েড"
    },
    "correctAnswer": "C"
  },
  {
    "id": 66,
    "question": "কোন উদ্ভিদের সমস্ত শরীরজুড়ে ক্লোরোপ্লাস্ট থাকে?",
    "options": {
      "A": "Riccia",
      "B": "Pteris",
      "C": "Oryza",
      "D": "Anthoceros"
    },
    "correctAnswer": "D"
  },
  {
    "id": 67,
    "question": "হাইডাথোড দেখা যায় কোন উদ্ভিদে?",
    "options": {
      "A": "আম-জাম",
      "B": "পেয়ারা-লিচু",
      "C": "জবা-ডালিম",
      "D": "কচু-টমেটো"
    },
    "correctAnswer": "D"
  },
  {
    "id": 68,
    "question": "মেসার্ক কোথায় দেখা যায়?",
    "options": {
      "A": "পাতায়",
      "B": "ফলে",
      "C": "মূলে",
      "D": "ফুলে"
    },
    "correctAnswer": "A"
  },
  {
    "id": 69,
    "question": "2 × 2 বর্গ ম্যাট্রিক্সের aᵢⱼ = { i+j : i ≠ j, 2i-j : i = j } হলে নিচের কোনটি সত্য?",
    "options": {
      "A": "[[1, 3], [3, 2]]",
      "B": "[[1, 2], [3, 3]]",
      "C": "[[1, 2], [3, 2]]",
      "D": "[[2, 3], [3, 1]]"
    },
    "correctAnswer": "A"
  },
  {
    "id": 70,
    "question": "∫ (from 1 to e) dx / (x(1+lnx)) = ?",
    "options": {
      "A": "e",
      "B": "e + 1",
      "C": "ln e + 1",
      "D": "ln 2"
    },
    "correctAnswer": "D"
  },
  {
    "id": 71,
    "question": "(x-7)² + (y-8)² = a² বৃত্তটি (-1, 2) বিন্দুগামী হলে এর ব্যাস নিচের কোনটি?",
    "options": {
      "A": "10",
      "B": "20",
      "C": "15",
      "D": "25"
    },
    "correctAnswer": "B"
  },
  {
    "id": 72,
    "question": "যদি tan θ = 5/12 এবং cos θ ধনাত্মক হয়, তবে (sin θ + cos(-θ)) / (sec(-θ) + tan θ) এর মান হবে-",
    "options": {
      "A": "34/39",
      "B": "34/40",
      "C": "30/39",
      "D": "35/50"
    },
    "correctAnswer": "A"
  },
  {
    "id": 73,
    "question": "y = |x| (x < 0) হলে dy/dx = ?",
    "options": {
      "A": "1",
      "B": "-1",
      "C": "0",
      "D": "কোনটিই নয়"
    },
    "correctAnswer": "B"
  },
  {
    "id": 74,
    "question": "কোন বিন্দুতে ক্রিয়ারত P ও 25N মানের দুইটি বলের লব্ধি 20N, যা P বলের দিকের সাথে সমকোণ উৎপন্ন করে। P-এর মান কত?",
    "options": {
      "A": "10N",
      "B": "20N",
      "C": "25N",
      "D": "15N"
    },
    "correctAnswer": "D"
  },
  {
    "id": 75,
    "question": "x = 1, x = 5, y = 4 এবং y = 8 রেখাগুলো দ্বারা গঠিত চতুর্ভুজের একটি কর্ণের ঢাল হবে-",
    "options": {
      "A": "0",
      "B": "1/2",
      "C": "1",
      "D": "-1/2"
    },
    "correctAnswer": "C"
  },
  {
    "id": 76,
    "question": "x² - 2x - 5 = 0 সমীকরণের মূলদ্বয় p, q হলে p - q =?",
    "options": {
      "A": "24",
      "B": "-24",
      "C": "√24",
      "D": "√34"
    },
    "correctAnswer": "C"
  },
  {
    "id": 77,
    "question": "ω যদি এককের একটি কাল্পনিক ঘনমূল হয়, তবে (1-ω+ω²)(1-ω²+ω⁴) এর মান হবে-",
    "options": {
      "A": "4",
      "B": "6",
      "C": "3",
      "D": "2"
    },
    "correctAnswer": "A"
  },
  {
    "id": 78,
    "question": "x/6 + y/5 = 1 সরলরেখাটি অক্ষদ্বয়ের সাথে যে ত্রিভুজ গঠন করে তার ক্ষেত্রফল কত বর্গ একক?",
    "options": {
      "A": "5",
      "B": "6",
      "C": "15",
      "D": "30"
    },
    "correctAnswer": "C"
  },
  {
    "id": 79,
    "question": "4x² + 5y² = 20 উপবৃত্তের উৎকেন্দ্রিকতা হবে-",
    "options": {
      "A": "1/√5",
      "B": "1/2",
      "C": "3/4",
      "D": "√5"
    },
    "correctAnswer": "A"
  },
  {
    "id": 80,
    "question": "y = 2x² + 3x + 1 বক্ররেখার (0, 1) বিন্দুতে অভিলম্বের ঢাল কত?",
    "options": {
      "A": "-3",
      "B": "-1/3",
      "C": "1/3",
      "D": "3"
    },
    "correctAnswer": "B"
  }
]
